redmine_ballcourt/__init__.py
redmine_ballcourt/config.py
redmine_ballcourt/redmine_ballcourt.py
redmine_ballcourt-0.2.2.dist-info/METADATA
redmine_ballcourt-0.2.2.dist-info/WHEEL
redmine_ballcourt-0.2.2.dist-info/entry_points.txt
redmine_ballcourt-0.2.2.dist-info/licenses/LICENSE
redmine_ballcourt-0.2.2.dist-info/RECORD
