Metadata-Version: 2.3
Name: redmine_ballcourt
Version: 0.2.2
Summary: The ball's in your court! Which Redmine tickets are explicitly assigned to you?
Project-URL: Homepage, https://github.com/telemarq/redmine_ballcourt
Project-URL: Issues, https://github.com/telemarq/redmine_ballcourt/issues
Author-email: Quentin Stafford-Fraser <quentin@telemarq.com>
License-File: LICENSE
Requires-Python: >=3.10
Requires-Dist: dynaconf
Requires-Dist: jinja2
Requires-Dist: python-redmine
